{
  "uuid": "http://arks.princeton.edu/ark:/88435/f4752j298",
  "dc_creator_sm": [
    "Central Intelligence Agency"
  ],
  "dc_description_s": "This is a map of Central and Southern Iraq, shown at a 1:1,000,000 scale. The map was created by the Central Intelligence Agency.",
  "dc_format_s": "Scanned Map",
  "dc_identifier_s": "f4752j298",
  "dc_language_s": "English",
  "dc_publisher_s": "Central Intelligence Agency",
  "dc_rights_s": "Public",
  "dc_subject_sm": [
    "Roads",
    "Railroads",
    "Transportation",
    "Administrative and Political Boundaries",
    "Historic Sites"
  ],
  "dc_title_s": "Central and southern Iraq, 2003",
  "dc_type_s": "Dataset",
  "dct_references_s": "{\"http://iiif.io/api/image\": \"https://geowebservices.princeton.edu/iiif/pulmap%2Ff4%2F75%2F2j%2F29%2F8%2F00000001.jp2%2Finfo.json\", \"http://schema.org/url\": \"http://arks.princeton.edu/ark:/88435/f4752j298\", \"http://www.opengis.net/cat/csw/csdgm\": \"https://geowebservices.princeton.edu/metadata/edu.princeton.arks/f4752j298/fgdc.xml\"}",
  "dct_spatial_sm": [
    "Central and Southern Iraq",
    "Iraq",
    "Middle East",
    "Asia"
  ],
  "dct_issued_s": "February 2003",
  "dct_provenance_s": "Princeton",
  "georss_box_s": "30 40 34 48",
  "georss_polygon_s": "34 40 34 48 30 48 30 40 34 40",
  "layer_slug_s": "princeton-f4752j298",
  "layer_id_s": "f4752j298",
  "layer_modified_dt": "2015-01-11T17:42:58Z",
  "layer_geom_type_s": "Image",
  "solr_geom": "ENVELOPE(40, 48, 34, 30)"
}