{
  "uuid": "http://arks.princeton.edu/ark:/88435/9306t121g",
  "dc_creator_sm": [
    "Sanborn Map Company"
  ],
  "dc_description_s": "This a Sanborn map of Northfield",
  "dc_format_s": "Scanned Map",
  "dc_identifier_s": "9306t121g",
  "dc_language_s": "English",
  "dc_publisher_s": "New York: Sanborn Map Company",
  "dc_rights_s": "Public",
  "dct_provenance_s": "Princeton",
  "dct_references_s": "{\"http://iiif.io/api/image\":\"https://geowebservices.princeton.edu/iiif/pulmap%2F93%2F06%2Ft1%2F21%2Fg%2F00000001.jp2%2Finfo.json\"}",
  "layer_id_s": "9306t121g",
  "layer_slug_s": "princeton-9306t121g",
  "layer_geom_type_s": "Image",
  "layer_modified_dt": "2015-01-18T17:02:12Z",
  "dc_subject_sm": [
    "Boundaries",
    "Structure",
    "Fire Insurance",
    "Sanborn"
  ],
  "dc_title_s": "Northfield, Atlantic County, New Jersey (Sheet 6)",
  "dc_type_s": "Image",
  "dct_spatial_sm": [
    "New Jersey",
    "Northfield"
  ],
  "dct_temporal_sm": [
    "1933"
  ],
  "georss_box_s": "39.353786 -74.580563 39.390959 -74.532028",
  "georss_polygon_s": "39.390959 -74.580563 39.390959 -74.532028 39.353786 -74.532028 39.353786 -74.580563 39.390959 -74.580563",
  "solr_geom": "ENVELOPE(-74.580563, -74.532028, 39.390959, 39.353786)",
  "solr_year_i": "1933"
}