{
  "uuid": "http://arks.princeton.edu/ark:/88435/fb494997d",
  "dc_creator_sm": "LeadDog Consulting, LLCtd.",
  "dc_description_s": "Beijing Shopping spots",
  "dc_format_s": "Shapefile",
  "dc_identifier_s": "fb494997d",
  "dc_language_s": "English",
  "dc_publisher_s": "LeadDog Consulting, LLC",
  "dc_rights_s": "Public",
  "dc_subject_sm": [
    "Business and economic",
    "Shopping"
  ],
  "dc_title_s": "Beijing Shopping spots",
  "dc_type_s": "Dataset",
  "dct_references_s": "{\"http://schema.org/downloadUrl\": \"https://geowebservices.princeton.edu/item/fb494997d/data.zip\", \"http://www.opengis.net/def/serviceType/ogc/wfs\": \"https://geowebservices.princeton.edu/pulmap-restricted/geoserver/wfs\", \"http://www.opengis.net/cat/csw/csdgm\": \"https://geowebservices.princeton.edu/metadata/edu.princeton.arks/fb494997d/fgdc.xml\", \"http://schema.org/url\": \"http://arks.princeton.edu/ark:/88435/fb494997d\", \"http://www.opengis.net/def/serviceType/ogc/wms\": \"https://geowebservices.princeton.edu/geoserver/pulmap-restricted/wms\"}",
  "dct_spatial_sm": [
    "China",
    "Beijing"
  ],
  "dct_issued_s": "2006",
  "dct_provenance_s": "Princeton",
  "georss_box_s": "39.721957 115.967032 40.464238 117.119218",
  "georss_polygon_s": "40.464238 115.967032 40.464238 117.119218 39.721957 117.119218 39.721957 115.967032 40.464238 115.967032",
  "layer_slug_s": "princeton-fb494997d",
  "layer_id_s": "pulmap-restricted:fb494997d",
  "layer_modified_dt": "2014-12-19T16:18:34Z",
  "layer_geom_type_s": "Point",
  "solr_geom": "ENVELOPE(115.967032, 117.119218, 40.464238, 39.721957)",
  "solr_year_i": "2006"
}