{
  "uuid": "http://arks.princeton.edu/ark:/88435/5h73pz50g",
  "dc_creator_sm": [
    "McClelland, D.,"
  ],
  "dc_description_s": "\"A\" diagram of a portion of Oregon Territory /",
  "dc_format_s": "Scanned Map",
  "dc_identifier_s": "5h73pz50g",
  "dc_rights_s": "Public",
  "dct_provenance_s": "Princeton",
  "dct_references_s": "{\"http://www.loc.gov/standards/marcxml\":\"https://geowebservices.princeton.edu/download/items/5h73pz50g/marc.xml\",\"http://iiif.io/api/image\":\"https://libimages1.princeton.edu/loris/pulmap%2F5h%2F73%2Fpz%2F50%2Fg%2F00000001.jp2/info.json\"}",
  "layer_id_s": "5h73pz50g",
  "layer_slug_s": "princeton-5h73pz50g",
  "layer_geom_type_s": "Image",
  "layer_modified_dt": "2015-01-21T22:24:04Z",
  "dc_title_s": "\"A\" diagram of a portion of Oregon Territory /",
  "dc_type_s": "Image",
  "dct_spatial_sm": [
    "Oregon",
    "Washington (State)"
  ],
  "dct_temporal_sm": [
    "1851"
  ],
  "georss_box_s": "41.991794 -124.7035409 46.299099 -116.4635039",
  "georss_polygon_s": "46.299099 -124.7035409 46.299099 -116.4635039 41.991794 -116.4635039 41.991794 -124.7035409 46.299099 -124.7035409",
  "solr_geom": "ENVELOPE(-124.7035409, -116.4635039, 46.299099, 41.991794)",
  "solr_year_i": "1851"
}
