{
  "uuid": "http://arks.princeton.edu/ark:/88435/gh93h1741",
  "dc_creator_sm": [
    "Sanborn Map Company"
  ],
  "dc_description_s": "This a Sanborn map of Woodstown",
  "dc_format_s": "Scanned Map",
  "dc_identifier_s": "gh93h1741",
  "dc_language_s": "English",
  "dc_publisher_s": "New York: Sanborn Map Company",
  "dc_rights_s": "Public",
  "dct_provenance_s": "Princeton",
  "dct_references_s": "{\"http://iiif.io/api/image\": \"https://geowebservices.princeton.edu/iiif/pulmap%2Fgh%2F93%2Fh1%2F74%2F1%2F00000001.jp2%2Finfo.json\"}",
  "layer_id_s": "gh93h1741",
  "layer_slug_s": "princeton-gh93h1741",
  "layer_geom_type_s": "Image",
  "layer_modified_dt": "2015-01-18T17:08:07Z",
  "dc_subject_sm": [
    "Boundaries",
    "Structure",
    "Fire Insurance",
    "Sanborn"
  ],
  "dc_title_s": "Woodstown, Salem County, New Jersey (Sheet 4).",
  "dc_type_s": "Image",
  "dct_spatial_sm": [
    "New Jersey",
    "Woodstown"
  ],
  "dct_temporal_sm": [
    "1909"
  ],
  "georss_box_s": "39.637336 -75.336228 39.663762 -75.314644",
  "georss_polygon_s": "39.663762 -75.336228 39.663762 -75.314644 39.637336 -75.314644 39.637336 -75.336228 39.663762 -75.336228",
  "solr_geom": "ENVELOPE(-75.336228, -75.314644, 39.663762, 39.637336)",
  "solr_year_i": "1909"
}