{
  "solr_year_i": "1884",
  "dc_description_s": "State of Oregon",
  "layer_modified_dt": "2015-01-19T22:36:40Z",
  "dc_creator_sm": [
    "Dinsmore, A. F.",
    "Naylor, William."
  ],
  "layer_id_s": "6969z260j",
  "dc_type_s": "Image",
  "dc_identifier_s": "6969z260j",
  "dct_provenance_s": "Princeton",
  "dc_title_s": "State of Oregon",
  "layer_slug_s": "princeton-6969z260j",
  "dc_format_s": "Scanned Map",
  "dct_references_s": "{\"http://www.loc.gov/standards/marcxml\": \"https://geowebservices.princeton.edu/download/items/6969z260j/marc.xml\", \"http://iiif.io/api/image\": \"https://libimages1.princeton.edu/loris/pulmap/69/69/z2/60/j/00000001.jp2/info.json\"}",
  "layer_geom_type_s": "Image",
  "dct_temporal_sm": [
    "1884"
  ],
  "solr_geom": "ENVELOPE(-124.75, -116.5, 46.25, 42.0)",
  "dc_rights_s": "Public",
  "dct_spatial_sm": [
    "Oregon"
  ],
  "geoblacklight_version": "1.0"
}