{
  "uuid": "http://arks.princeton.edu/ark:/88435/41687k890",
  "dc_creator_sm": [
    "Valentine, D. T.",
    "Fox, N. B.,"
  ],
  "dc_description_s": "Part of New-York in 1742 : showing the site of the present park, the collect and little collect ponds, and a portion of the west side of Broadway",
  "dc_format_s": "Scanned Map",
  "dc_identifier_s": "41687k890",
  "dc_rights_s": "Public",
  "dct_provenance_s": "Princeton",
  "dct_references_s": "{\"http://www.loc.gov/standards/marcxml\": \"https://geowebservices.princeton.edu/metadata/edu.princeton.arks/41687k890/marc.xml\", \"http://iiif.io/api/image\": \"https://geowebservices.princeton.edu/iiif/pulmap%2F41%2F68%2F7k%2F89%2F0%2F00000001.jp2%2Finfo.json\"}",
  "layer_id_s": "41687k890",
  "layer_slug_s": "princeton-41687k890",
  "layer_geom_type_s": "Image",
  "layer_modified_dt": "2015-01-21T22:24:04Z",
  "dc_title_s": "Part of New-York in 1742 : showing the site of the present park, the collect and little collect ponds, and a portion of the west side of Broadway",
  "dc_type_s": "Image",
  "dct_spatial_sm": [
    "Manhattan (New York, N.Y.)",
    "New York (N.Y.)"
  ],
  "dct_temporal_sm": "1856",
  "georss_box_s": "40.7702778 -73.9797222 40.8102778 -73.9397222",
  "georss_polygon_s": "40.8102778 -73.9797222 40.8102778 -73.9397222 40.7702778 -73.9397222 40.7702778 -73.9797222 40.8102778 -73.9797222",
  "solr_geom": "ENVELOPE(-73.9797222, -73.9397222, 40.8102778, 40.7702778)",
  "solr_year_i": "1856"
}