{
  "uuid": "http://arks.princeton.edu/ark:/88435/4j03d2206",
  "dc_description_s": "Carta di Lombardia, Piemonte, Liguria",
  "dc_format_s": "Scanned Map",
  "dc_identifier_s": "4j03d2206",
  "dc_rights_s": "Public",
  "dct_provenance_s": "Princeton",
  "dct_references_s": "{\"http://www.loc.gov/standards/marcxml\": \"https://geowebservices.princeton.edu/metadata/edu.princeton.arks/4j03d2206/marc.xml\", \"http://iiif.io/api/image\": \"https://geowebservices.princeton.edu/iiif/pulmap%2F4j%2F03%2Fd2%2F20%2F6%2F00000001.jp2%2Finfo.json\"}",
  "layer_id_s": "4j03d2206",
  "layer_slug_s": "princeton-4j03d2206",
  "layer_geom_type_s": "Image",
  "layer_modified_dt": "2015-01-25T02:06:23Z",
  "dc_title_s": "Carta di Lombardia, Piemonte, Liguria",
  "dc_type_s": "Image",
  "dct_spatial_sm": [
    "Italy, Northern",
    "Lombardy (Italy)",
    "Piedmont (Italy)",
    "Liguria (Italy)"
  ],
  "dct_temporal_sm": "1905",
  "georss_box_s": "42.6792426623 6.6267201 47.092 18.5205015",
  "georss_polygon_s": "47.092 6.6267201 47.092 18.5205015 42.6792426623 18.5205015 42.6792426623 6.6267201 47.092 6.6267201",
  "solr_geom": "ENVELOPE(6.6267201, 18.5205015, 47.092, 42.6792426623)",
  "solr_year_i": "1905"
}