{
  "uuid": "http://arks.princeton.edu/ark:/88435/xk81jn87f",
  "dc_description_s": "Delineatio aureae Sterilitatis Herciniensis, i. e. Herciniae Metalliferæ accurata chorographia : omnes simul fodinas & loca nativa minerarum, quæ ibi effodiuntur, addita nomenclatura, distincte exhibens",
  "dc_format_s": "Scanned Map",
  "dc_identifier_s": "xk81jn87f",
  "dc_rights_s": "Public",
  "dct_provenance_s": "Princeton",
  "dct_references_s": "{\"http://www.loc.gov/standards/marcxml\":\"https://geowebservices.princeton.edu/download/items/xk81jn87f/marc.xml\",\"http://iiif.io/api/image\":\"https://libimages1.princeton.edu/loris/pulmap%2Fxk%2F81%2Fjn%2F87%2Ff%2F00000001.jp2/info.json\"}",
  "layer_id_s": "xk81jn87f",
  "layer_slug_s": "princeton-xk81jn87f",
  "layer_geom_type_s": "Image",
  "layer_modified_dt": "2015-01-21T22:24:20Z",
  "dc_title_s": "Delineatio aureae Sterilitatis Herciniensis, i. e. Herciniae Metalliferæ accurata chorographia : omnes simul fodinas & loca nativa minerarum, quæ ibi effodiuntur, addita nomenclatura, distincte exhibens",
  "dc_type_s": "Image",
  "dct_spatial_sm": [
    "Harz Mountains (Germany)"
  ],
  "dct_temporal_sm": [
    "1737"
  ],
  "georss_box_s": "51.4367989189 10.1499125055 51.965275368 11.6057957062",
  "georss_polygon_s": "51.965275368 10.1499125055 51.965275368 11.6057957062 51.4367989189 11.6057957062 51.4367989189 10.1499125055 51.965275368 10.1499125055",
  "solr_geom": "ENVELOPE(10.1499125055, 11.6057957062, 51.965275368, 51.4367989189)",
  "solr_year_i": "1737"
}
