{
  "uuid": "http://arks.princeton.edu/ark:/88435/j3860941r",
  "dc_creator_sm": [
    "Hondius, Jodocus,",
    "Mercator, Gerhard,",
    "McCabe, Robert A.,"
  ],
  "dc_description_s": "Persici vel Sophorum regni typus",
  "dc_format_s": "Scanned Map",
  "dc_identifier_s": "j3860941r",
  "dc_rights_s": "Public",
  "dct_provenance_s": "Princeton",
  "dct_references_s": "{\"http://www.loc.gov/standards/marcxml\": \"https://geowebservices.princeton.edu/metadata/edu.princeton.arks/j3860941r/marc.xml\", \"http://iiif.io/api/image\": \"https://geowebservices.princeton.edu/iiif/pulmap%2F3%2F86%2F09%2F41%2Fr%2F00000001.jp2%2Finfo.json\"}",
  "layer_id_s": "j3860941r",
  "layer_slug_s": "princeton-j3860941r",
  "layer_geom_type_s": "Image",
  "layer_modified_dt": "2015-01-21T22:24:11Z",
  "dc_title_s": "Persici vel Sophorum regni typus",
  "dc_type_s": "Image",
  "dct_spatial_sm": [
    "Afghanistan",
    "Iran",
    "Pakistan"
  ],
  "dct_temporal_sm": "1613",
  "georss_box_s": "29.388333 60.503889 38.4899217 74.889862",
  "georss_polygon_s": "38.4899217 60.503889 38.4899217 74.889862 29.388333 74.889862 29.388333 60.503889 38.4899217 60.503889",
  "solr_geom": "ENVELOPE(60.503889, 74.889862, 38.4899217, 29.388333)",
  "solr_year_i": "1613"
}