{
  "uuid": "http://arks.princeton.edu/ark:/88435/bc386k79f",
  "dc_creator_sm": [
    "Defense Mapping Agency"
  ],
  "dc_description_s": "This is a map of the city of Bluefields, Nicaragua, shown at a 1:12,500 scale. The map was created for use by Department of Defense by the Defense Mapping Agency.",
  "dc_format_s": "Scanned Map",
  "dc_identifier_s": "bc386k79f",
  "dc_language_s": "English",
  "dc_publisher_s": "Defense Mapping Agency",
  "dc_rights_s": "Public",
  "dc_subject_sm": [
    "Roads",
    "Railroads",
    "Transportation",
    "Industry",
    "City map",
    "Military",
    "Facilities and Structures"
  ],
  "dc_title_s": "Nicaragua city graphic 1:12,500. Bluefields. Series E956. ",
  "dc_type_s": "Dataset",
  "dct_references_s": "{\"http://iiif.io/api/image\":\"https://geowebservices.princeton.edu/iiif/pulmap%2Fbc%2F38%2F6k%2F79%2Ff%2F00000001.jp2%2Finfo.json\",\"http://www.opengis.net/cat/csw/csdgm\":\"https://geowebservices.princeton.edu/download/items/bc386k79f/fgdc.xml\",\"http://schema.org/thumbnailUrl\":\"https://geowebservices.princeton.edu/download/items/bc386k79f/preview.jpg\"}",
  "dct_spatial_sm": [
    "Bluefields",
    "Zelaya",
    "Region Autonoma Atlantico",
    "Nicaragua"
  ],
  "dct_issued_s": "1992",
  "dct_provenance_s": "Princeton",
  "georss_box_s": "11.9667 -83.7833 12.0333 -83.7333",
  "georss_polygon_s": "12.0333 -83.7833 12.0333 -83.7333 11.9667 -83.7333 11.9667 -83.7833 12.0333 -83.7833",
  "layer_slug_s": "princeton-bc386k79f",
  "layer_id_s": "bc386k79f",
  "layer_modified_dt": "2015-01-11T17:43:01Z",
  "layer_geom_type_s": "Image",
  "solr_geom": "ENVELOPE(-83.7833, -83.7333, 12.0333, 11.9667)",
  "solr_year_i": "1992"
}