{
  "solr_year_i": "1854",
  "dc_description_s": "Africa, North part : Africa, South part",
  "layer_modified_dt": "2015-01-21T22:23:42Z",
  "dc_creator_sm": [
    "Hall, Sidney,"
  ],
  "layer_id_s": "4b29b781q",
  "dc_type_s": "Image",
  "dc_identifier_s": "4b29b781q",
  "dct_provenance_s": "Princeton",
  "dc_title_s": "Africa, North part : Africa, South part",
  "layer_slug_s": "princeton-4b29b781q",
  "dc_format_s": "Scanned Map",
  "dct_references_s": "{\"http://www.loc.gov/standards/marcxml\": \"https://geowebservices.princeton.edu/download/items/4b29b781q/marc.xml\", \"http://iiif.io/api/image\": \"https://libimages.princeton.edu/loris/pulmap/4b/29/b7/81/q/00000001.jp2/info.json\"}",
  "layer_geom_type_s": "Image",
  "dct_temporal_sm": [
    "1854"
  ],
  "solr_geom": "ENVELOPE(16.45194, 38.0037335, -22.12503, -46.9813794)",
  "dc_rights_s": "Public",
  "dct_spatial_sm": [
    "South Africa",
    "Africa, Northwest",
    "Morocco",
    "Algeria",
    "Tunisia"
  ],
  "geoblacklight_version": "1.0"
}
