{
  "uuid": "http://arks.princeton.edu/ark:/88435/pv63g274b",
  "dc_creator_sm": [
    "Morris, William H.,",
    "Stockdale, John,"
  ],
  "dc_description_s": "A map of Durham : from the best authorities",
  "dc_format_s": "Scanned Map",
  "dc_identifier_s": "pv63g274b",
  "dc_rights_s": "Public",
  "dct_provenance_s": "Princeton",
  "dct_references_s": "{\"http://www.loc.gov/standards/marcxml\":\"https://geowebservices.princeton.edu/download/items/pv63g274b/marc.xml\",\"http://iiif.io/api/image\":\"https://geowebservices.princeton.edu/iiif/pulmap%2Fpv%2F63%2Fg2%2F74%2F00000001.jp2%2Finfo.json\"}",
  "layer_id_s": "pv63g274b",
  "layer_slug_s": "princeton-pv63g274b",
  "layer_geom_type_s": "Image",
  "layer_modified_dt": "2015-01-21T22:24:18Z",
  "dc_title_s": "A map of Durham : from the best authorities",
  "dc_type_s": "Image",
  "dct_spatial_sm": [
    "Durham (England : County)"
  ],
  "dct_temporal_sm": [
    "1805"
  ],
  "georss_box_s": "54.6164152 -1.7358539 54.9364152 -1.4158539",
  "georss_polygon_s": "54.9364152 -1.7358539 54.9364152 -1.4158539 54.6164152 -1.4158539 54.6164152 -1.7358539 54.9364152 -1.7358539",
  "solr_geom": "ENVELOPE(-1.7358539, -1.4158539, 54.9364152, 54.6164152)",
  "solr_year_i": "1805"
}