{
  "solr_year_i": "1663",
  "dc_description_s": "Territorio di Bologna",
  "layer_modified_dt": "2015-01-25T02:06:20Z",
  "dc_creator_sm": [
    "Blaeu, Joan,"
  ],
  "layer_id_s": "js956j36c",
  "dc_type_s": "Image",
  "dc_identifier_s": "js956j36c",
  "dct_provenance_s": "Princeton",
  "dc_title_s": "Territorio di Bologna",
  "layer_slug_s": "princeton-js956j36c",
  "dc_format_s": "Scanned Map",
  "dct_references_s": "{\"http://www.loc.gov/standards/marcxml\": \"https://geowebservices.princeton.edu/download/items/js956j36c/marc.xml\", \"http://iiif.io/api/image\": \"https://libimages.princeton.edu/loris/pulmap/js/95/6j/36/c/00000001.jp2/info.json\"}",
  "layer_geom_type_s": "Image",
  "dct_temporal_sm": [
    "1663"
  ],
  "solr_geom": "ENVELOPE(10.8066008, 11.841408, 44.8056876, 44.0622557)",
  "dc_rights_s": "Public",
  "dct_spatial_sm": [
    "Bologna (Italy : Province)"
  ],
  "geoblacklight_version": "1.0"
}
