{
  "uuid": "http://arks.princeton.edu/ark:/88435/cj82k8803",
  "dc_creator_sm": "Central Intelligence Agency",
  "dc_description_s": "This is a map of Afghanistan with relief. The map was created by the Central Intelligence Agency.",
  "dc_format_s": "Scanned Map",
  "dc_identifier_s": "cj82k8803",
  "dc_language_s": "English",
  "dc_publisher_s": "Central Intelligence Agency",
  "dc_rights_s": "Public",
  "dc_subject_sm": [
    "Roads",
    "Railroads",
    "Transportation",
    "Administrative and Political Boundaries"
  ],
  "dc_title_s": "Afghanistan, 2003",
  "dc_type_s": "Dataset",
  "dct_references_s": "{\"http://iiif.io/api/image\": \"https://geowebservices.princeton.edu/iiif/pulmap%2Fcj%2F82%2Fk8%2F80%2F3%2F00000001.jp2%2Finfo.json\", \"http://schema.org/url\": \"http://arks.princeton.edu/ark:/88435/cj82k8803\", \"http://www.opengis.net/cat/csw/csdgm\": \"https://geowebservices.princeton.edu/metadata/edu.princeton.arks/cj82k8803/fgdc.xml\"}",
  "dct_spatial_sm": [
    "Afghanistan",
    "Middle East",
    "Asia"
  ],
  "dct_issued_s": "June 2003",
  "dct_provenance_s": "Princeton",
  "georss_box_s": "30 60 40 75",
  "georss_polygon_s": "40 60 40 75 30 75 30 60 40 60",
  "layer_slug_s": "princeton-cj82k8803",
  "layer_id_s": "cj82k8803",
  "layer_modified_dt": "2015-01-11T17:42:48Z",
  "layer_geom_type_s": "Image",
  "solr_geom": "ENVELOPE(60, 75, 40, 30)"
}