{
  "uuid": "http://arks.princeton.edu/ark:/88435/q811kn074",
  "dc_creator_sm": [
    "Guicciardini, Lodovico,"
  ],
  "dc_description_s": "Antwerpiae nobilissimi totius orbis terrarau[m] emporii typus anno M.D.XCVIII",
  "dc_format_s": "Scanned Map",
  "dc_identifier_s": "q811kn074",
  "dc_rights_s": "Public",
  "dct_provenance_s": "Princeton",
  "dct_references_s": "{\"http://www.loc.gov/standards/marcxml\":\"https://geowebservices.princeton.edu/download/items/q811kn074/marc.xml\",\"http://iiif.io/api/image\":\"https://libimages1.princeton.edu/loris/pulmap%2Fq8%2F11%2Fkn%2F07%2F4%2F00000001.jp2/info.json\"}",
  "layer_id_s": "q811kn074",
  "layer_slug_s": "princeton-q811kn074",
  "layer_geom_type_s": "Image",
  "layer_modified_dt": "2015-01-21T22:24:10Z",
  "dc_title_s": "Antwerpiae nobilissimi totius orbis terrarau[m] emporii typus anno M.D.XCVIII",
  "dc_type_s": "Image",
  "dct_spatial_sm": [
    "Antwerp (Belgium)"
  ],
  "dct_temporal_sm": [
    "1625"
  ],
  "georss_box_s": "51.1432868 4.2175769 51.3776412 4.497986",
  "georss_polygon_s": "51.3776412 4.2175769 51.3776412 4.497986 51.1432868 4.497986 51.1432868 4.2175769 51.3776412 4.2175769",
  "solr_geom": "ENVELOPE(4.2175769, 4.497986, 51.3776412, 51.1432868)",
  "solr_year_i": "1625"
}
