{
  "dc_creator_sm": [
    "Boundary Solutions, Inc."
  ],
  "dc_description_s": "Tax Parcels in Yuma County, 2008, with assessor's data attached.",
  "dc_format_s": "Shapefile",
  "dc_identifier_s": "1z40kv396",
  "dc_language_s": "English",
  "dc_rights_s": "Restricted",
  "dc_subject_sm": [
    "parcels",
    "tax parcels",
    "property maps",
    "cadastral maps",
    "parcel",
    "ownership",
    "property",
    "land value",
    "Planning and Cadastral"
  ],
  "dc_title_s": "Yuma County, Arizona land parcels, 2008",
  "dc_type_s": "Dataset",
  "dct_references_s": "{\"http://schema.org/downloadUrl\":\"https://geowebservices.princeton.edu/download/items/1z40kv396/data.zip\",\"http://www.opengis.net/def/serviceType/ogc/wfs\":\"https://geowebservices.princeton.edu/pulmap-restricted/geoserver/wfs\",\"http://www.opengis.net/cat/csw/csdgm\":\"https://geowebservices.princeton.edu/download/items/1z40kv396/fgdc.xml\",\"http://www.opengis.net/def/serviceType/ogc/wms\":\"https://geowebservices.princeton.edu/pulmap-restricted/geoserver/wms\",\"http://schema.org/thumbnailUrl\":\"https://geowebservices.princeton.edu/download/items/1z40kv396/preview.jpg\"}",
  "dct_spatial_sm": [
    "Arizona",
    "Yuma County",
    "Yuma"
  ],
  "dct_issued_s": "20080818",
  "dct_provenance_s": "Princeton",
  "layer_slug_s": "princeton-1z40kv396",
  "layer_id_s": "pulmap-restricted:1z40kv396",
  "layer_modified_dt": "2014-12-19T16:18:37Z",
  "layer_geom_type_s": "Polygon",
  "solr_geom": "ENVELOPE(-114.813576, -113.326330, 33.464459, 32.040805)",
  "geoblacklight_version": "1.0"
}
