{
  "uuid": "http://arks.princeton.edu/ark:/88435/gf06g520t",
  "dc_description_s": "Coffee map of the Republic of Colombia world's largest producer of mild coffees /",
  "dc_format_s": "Scanned Map",
  "dc_identifier_s": "gf06g520t",
  "dc_rights_s": "Public",
  "dct_provenance_s": "Princeton",
  "dct_references_s": "{\"http://www.loc.gov/standards/marcxml\": \"https://geowebservices.princeton.edu/metadata/edu.princeton.arks/gf06g520t/marc.xml\", \"http://iiif.io/api/image\": \"https://geowebservices.princeton.edu/iiif/pulmap%2Fgf%2F06%2Fg5%2F20%2Ft%2F00000001.jp2%2Finfo.json\"}",
  "layer_id_s": "gf06g520t",
  "layer_slug_s": "princeton-gf06g520t",
  "layer_geom_type_s": "Image",
  "layer_modified_dt": "2015-01-23T17:48:40Z",
  "dc_title_s": "Coffee map of the Republic of Colombia world's largest producer of mild coffees /",
  "dc_type_s": "Image",
  "dct_spatial_sm": [
    "Colombia",
    "Colombia"
  ],
  "dct_temporal_sm": [
    "1939"
  ],
  "georss_box_s": "-3.0 -5.66666666667 12.8333333333 -9.16666666667",
  "georss_polygon_s": "12.8333333333 -5.66666666667 12.8333333333 -9.16666666667 -3.0 -9.16666666667 -3.0 -5.66666666667 12.8333333333 -5.66666666667",
  "solr_geom": "ENVELOPE(-5.66666666667, -9.16666666667, 12.8333333333, -3.0)",
  "solr_year_i": "1939"
}