{
  "solr_year_i": "1763",
  "dc_description_s": "Carte de l'Isle de Cayenne",
  "layer_modified_dt": "2015-01-21T22:24:07Z",
  "layer_id_s": "gx41mm311",
  "dc_type_s": "Image",
  "dc_identifier_s": "gx41mm311",
  "dct_provenance_s": "Princeton",
  "dc_title_s": "Carte de l'Isle de Cayenne",
  "layer_slug_s": "princeton-gx41mm311",
  "dc_format_s": "Scanned Map",
  "dct_references_s": "{\"http://www.loc.gov/standards/marcxml\": \"https://geowebservices.princeton.edu/download/items/gx41mm311/marc.xml\", \"http://iiif.io/api/image\": \"https://libimages.princeton.edu/loris/pulmap/gx/41/mm/31/1/00000001.jp2/info.json\"}",
  "layer_geom_type_s": "Image",
  "dct_temporal_sm": [
    "1763"
  ],
  "solr_geom": "ENVELOPE(-52.5937857, -52.2805193, 5.2972653, 4.887855)",
  "dc_rights_s": "Public",
  "dct_spatial_sm": [
    "Cayenne (French Guiana)"
  ],
  "geoblacklight_version": "1.0"
}
