{
  "uuid": "http://arks.princeton.edu/ark:/88435/8s45qb68d",
  "dc_creator_sm": [
    "Smith, William,",
    "Jacobs, S.",
    "Dalmont, I."
  ],
  "dc_description_s": "Peloponnesus",
  "dc_format_s": "Scanned Map",
  "dc_identifier_s": "8s45qb68d",
  "dc_rights_s": "Public",
  "dct_provenance_s": "Princeton",
  "dct_references_s": "{\"http://www.loc.gov/standards/marcxml\": \"https://geowebservices.princeton.edu/metadata/edu.princeton.arks/8s45qb68d/marc.xml\", \"http://iiif.io/api/image\": \"https://geowebservices.princeton.edu/iiif/pulmap%2F8s%2F45%2Fqb%2F68%2Fd%2F00000001.jp2%2Finfo.json\"}",
  "layer_id_s": "8s45qb68d",
  "layer_slug_s": "princeton-8s45qb68d",
  "layer_geom_type_s": "Image",
  "layer_modified_dt": "2015-01-21T22:23:49Z",
  "dc_title_s": "Peloponnesus",
  "dc_type_s": "Image",
  "dct_spatial_sm": "Peloponnesus (Greece : Peninsula)",
  "dct_temporal_sm": "1872",
  "georss_box_s": "36.2864096 19.2477876 40.0018586 23.454616",
  "georss_polygon_s": "40.0018586 19.2477876 40.0018586 23.454616 36.2864096 23.454616 36.2864096 19.2477876 40.0018586 19.2477876",
  "solr_geom": "ENVELOPE(19.2477876, 23.454616, 40.0018586, 36.2864096)",
  "solr_year_i": "1872"
}