{
  "dc_description_s": "This is a map of the city of Delhi, India, shown at a 1:50,000 scale. The map was created by the government-sponsored Survey of India.",
  "layer_modified_dt": "2015-01-11T18:24:52Z",
  "solr_geom": "ENVELOPE(77.0000, 77.4333, 28.7167, 28.3500)",
  "dct_references_s": "{\"http://schema.org/url\": \"http://arks.princeton.edu/ark:/88435/8w32r7179\", \"http://www.opengis.net/cat/csw/csdgm\": \"https://geowebservices.princeton.edu/metadata/edu.princeton.arks/8w32r7179/fgdc.xml\"}",
  "dc_rights_s": "Restricted",
  "uuid": "http://arks.princeton.edu/ark:/88435/8w32r7179",
  "dct_provenance_s": "Princeton",
  "dc_subject_sm": [
    "City plan",
    "Topography",
    "elevation"
  ],
  "dc_format_s": "Scanned Map",
  "dct_issued_s": "1996",
  "dc_creator_sm": "Survey of India",
  "dc_type_s": "Image",
  "dc_identifier_s": "8w32r7179",
  "georss_polygon_s": "28.7167 77.0000 28.7167 77.4333 28.3500 77.4333 28.3500 77.0000 28.7167 77.0000",
  "dc_publisher_s": "Survey of India",
  "solr_year_i": "1996",
  "dct_spatial_sm": [
    "New Delhi",
    "New Dilli",
    "Najafgarh",
    "Gurgaon",
    "Noida",
    "Faridabad",
    "Dadri",
    "Ghaziarbad Dist.",
    "Delhi Nat. Capital Territory",
    "Uttar Pradesh State",
    "Haryana State",
    "India",
    "MAX  G7654.D5C2.1996.S9I5 (b)"
  ],
  "layer_id_s": "8w32r7179",
  "georss_box_s": "28.3500 77.0000 28.7167 77.4333",
  "dc_title_s": "Delhi & its environs.",
  "layer_slug_s": "princeton-8w32r7179",
  "layer_geom_type_s": "Image",
  "dc_language_s": "English"
}
