{
  "uuid": "http://arks.princeton.edu/ark:/88435/q237ht707",
  "dc_creator_sm": [
    "Army Map Service"
  ],
  "dc_description_s": "This is a map of the city of Misurata, Tripolitania, shown at a 1:5,000 scale. The map was created for use by War and Navy Department agencies during World War II.",
  "dc_format_s": "Scanned Map",
  "dc_identifier_s": "q237ht707",
  "dc_language_s": "English",
  "dc_publisher_s": "Army Map Service",
  "dc_rights_s": "Public",
  "dc_subject_sm": [
    "Roads",
    "Railroads",
    "Transportation",
    "Industry",
    "World War II",
    "City map",
    "Military",
    "Facilities and Structures"
  ],
  "dc_title_s": "Tripolitania 1:5,000. Misurata city plan. G.S.G.S. 4374.",
  "dc_type_s": "Dataset",
  "dct_references_s": "{\"http://iiif.io/api/image\": \"https://geowebservices.princeton.edu/iiif/pulmap%2Fq2%2F37%2Fht%2F70%2F7%2F00000001.jp2%2Finfo.json\", \"http://schema.org/url\": \"http://arks.princeton.edu/ark:/88435/q237ht707\", \"http://www.opengis.net/cat/csw/csdgm\": \"https://geowebservices.princeton.edu/metadata/edu.princeton.arks/q237ht707/fgdc.xml\"}",
  "dct_spatial_sm": [
    "Misurata",
    "Misratah",
    "Libya",
    "Lybia",
    "Tripolitania"
  ],
  "dct_issued_s": "1943",
  "dct_provenance_s": "Princeton",
  "georss_box_s": "32.3667 15.0833 32.3833 15.200",
  "georss_polygon_s": "32.3833 15.0833 32.3833 15.200 32.3667 15.200 32.3667 15.0833 32.3833 15.0833",
  "layer_slug_s": "princeton-q237ht707",
  "layer_id_s": "q237ht707",
  "layer_modified_dt": "2015-01-11T17:43:38Z",
  "layer_geom_type_s": "Image",
  "solr_geom": "ENVELOPE(15.0833, 15.200, 32.3833, 32.3667)",
  "solr_year_i": "1943"
}