{
  "uuid": "http://arks.princeton.edu/ark:/88435/gb19f746k",
  "dc_creator_sm": [
    "LeadDog Consulting, LLC"
  ],
  "dc_description_s": "Pakistan Province Boundary. This LeadDog dataset is released Semi-Annually.",
  "dc_format_s": "Shapefile",
  "dc_identifier_s": "gb19f746k",
  "dc_language_s": "English",
  "dc_rights_s": "Restricted",
  "dc_subject_sm": [
    "Location",
    "Boundaries",
    "Location",
    "Province Boundary",
    "Roadmap",
    "Navigation",
    "Routing",
    "Geocoding",
    "LeadDog",
    "Provinces"
  ],
  "dc_title_s": "Pakistan Province Boundary, 2010",
  "dc_type_s": "Dataset",
  "dct_references_s": "{\"http://schema.org/downloadUrl\":\"https://geowebservices.princeton.edu/download/items/gb19f746k/data.zip\",\"http://www.opengis.net/def/serviceType/ogc/wfs\":\"https://geowebservices.princeton.edu/pulmap-restricted/geoserver/wfs\",\"http://www.opengis.net/cat/csw/csdgm\":\"https://geowebservices.princeton.edu/download/items/gb19f746k/fgdc.xml\",\"http://www.opengis.net/def/serviceType/ogc/wms\":\"https://geowebservices.princeton.edu/pulmap-restricted/geoserver/wms\",\"http://schema.org/thumbnailUrl\":\"https://geowebservices.princeton.edu/download/items/gb19f746k/preview.jpg\"}",
  "dct_spatial_sm": [
    "PAKISTAN"
  ],
  "dct_issued_s": "20100101",
  "dct_provenance_s": "Princeton",
  "georss_box_s": "23.693722 60.893558 37.093082 79.285512",
  "layer_slug_s": "princeton-gb19f746k",
  "layer_id_s": "pulmap-restricted:gb19f746k",
  "layer_modified_dt": "2014-12-23T15:21:30Z",
  "layer_geom_type_s": "Polygon",
  "solr_geom": "ENVELOPE(60.893558, 79.285512, 37.093082, 23.693722)"
}