{
  "solr_year_i": "1917",
  "dc_description_s": "Map of Shanghai-Nanking and Shanghai-Hangchow-Ningpo railways with branch lines and tables.",
  "layer_modified_dt": "2015-01-21T22:24:23Z",
  "dc_creator_sm": [
    "Find, John T."
  ],
  "layer_id_s": "9w032554w",
  "dc_type_s": "Image",
  "dc_identifier_s": "9w032554w",
  "dct_provenance_s": "Princeton",
  "dc_title_s": "Map of Shanghai-Nanking and Shanghai-Hangchow-Ningpo railways with branch lines and tables.",
  "layer_slug_s": "princeton-9w032554w",
  "dc_format_s": "Scanned Map",
  "dct_references_s": "{\"http://www.loc.gov/standards/marcxml\": \"https://geowebservices.princeton.edu/download/items/9w032554w/marc.xml\", \"http://iiif.io/api/image\": \"https://libimages1.princeton.edu/loris/pulmap/9w/03/25/54/w/00000001.jp2/info.json\"}",
  "layer_geom_type_s": "Image",
  "dct_temporal_sm": [
    "1917"
  ],
  "solr_geom": "ENVELOPE(73.4997347, 134.7754563, 53.5608154, 3.966232)",
  "dc_rights_s": "Public",
  "dct_spatial_sm": [
    "China"
  ],
  "geoblacklight_version": "1.0"
}