{
  "uuid": "http://arks.princeton.edu/ark:/88435/6w924f288",
  "dc_creator_sm": [
    "Harrison, William,",
    "Carey, Mathew,"
  ],
  "dc_description_s": "A map of the United States : compiled chiefly from the state maps and other authentic information",
  "dc_format_s": "Scanned Map",
  "dc_identifier_s": "6w924f288",
  "dc_rights_s": "Public",
  "dct_provenance_s": "Princeton",
  "dct_references_s": "{\"http://www.loc.gov/standards/marcxml\": \"https://geowebservices.princeton.edu/metadata/edu.princeton.arks/6w924f288/marc.xml\", \"http://iiif.io/api/image\": \"https://geowebservices.princeton.edu/iiif/pulmap%2F6w%2F92%2F4f%2F28%2F8%2F00000001.jp2%2Finfo.json\"}",
  "layer_id_s": "6w924f288",
  "layer_slug_s": "princeton-6w924f288",
  "layer_geom_type_s": "Image",
  "layer_modified_dt": "2015-01-19T22:37:15Z",
  "dc_title_s": "A map of the United States : compiled chiefly from the state maps and other authentic information",
  "dc_type_s": "Image",
  "dct_spatial_sm": "East (U.S.)",
  "dct_temporal_sm": "1795",
  "georss_box_s": "25.0 -100.0 45.0 -60.0",
  "georss_polygon_s": "45.0 -100.0 45.0 -60.0 25.0 -60.0 25.0 -100.0 45.0 -100.0",
  "solr_geom": "ENVELOPE(-100.0, -60.0, 45.0, 25.0)",
  "solr_year_i": "1795"
}