{
  "solr_year_i": "1525",
  "dc_description_s": "[Greece]",
  "layer_modified_dt": "2015-01-21T22:23:46Z",
  "dc_creator_sm": [
    "Ptolemy,"
  ],
  "layer_id_s": "8c97ks27x",
  "dc_type_s": "Image",
  "dc_identifier_s": "8c97ks27x",
  "dct_provenance_s": "Princeton",
  "dc_title_s": "[Greece]",
  "layer_slug_s": "princeton-8c97ks27x",
  "dc_format_s": "Scanned Map",
  "dct_references_s": "{\"http://www.loc.gov/standards/marcxml\": \"https://geowebservices.princeton.edu/download/items/8c97ks27x/marc.xml\", \"http://iiif.io/api/image\": \"https://libimages.princeton.edu/loris/pulmap/8c/97/ks/27/x/00000001.jp2/info.json\"}",
  "layer_geom_type_s": "Image",
  "dct_temporal_sm": [
    "1525"
  ],
  "solr_geom": "ENVELOPE(22.4993729, 28.3309422, 40.901786, 35.59933)",
  "dc_rights_s": "Public",
  "dct_spatial_sm": [
    "Aegean Sea",
    "Adriatic Sea",
    "Greece",
    "Balkan Peninsula"
  ],
  "geoblacklight_version": "1.0"
}
