{
  "uuid": "http://arks.princeton.edu/ark:/88435/hq37vq27q",
  "dc_creator_sm": [
    "Boundary Solutions, Inc."
  ],
  "dc_description_s": "Roads and highways in Cass County, North Dakota, 2010.",
  "dc_format_s": "Shapefile",
  "dc_identifier_s": "hq37vq27q",
  "dc_language_s": "English",
  "dc_rights_s": "Public",
  "dc_subject_sm": [
    "roads",
    "highways",
    "line",
    "Transportation"
  ],
  "dc_title_s": "Cass County, North Dakota roads, 2010",
  "dc_type_s": "Dataset",
  "dct_references_s": "{\"http://schema.org/downloadUrl\": \"https://geowebservices.princeton.edu/item/hq37vq27q/data.zip\", \"http://www.opengis.net/def/serviceType/ogc/wfs\": \"https://geowebservices.princeton.edu/pulmap-restricted/geoserver/wfs\", \"http://www.opengis.net/cat/csw/csdgm\": \"https://geowebservices.princeton.edu/metadata/edu.princeton.arks/hq37vq27q/fgdc.xml\", \"http://schema.org/url\": \"http://arks.princeton.edu/ark:/88435/hq37vq27q\", \"http://www.opengis.net/def/serviceType/ogc/wms\": \"https://geowebservices.princeton.edu/geoserver/pulmap-restricted/wms\"}",
  "dct_spatial_sm": [
    "North Dakota",
    "Cass",
    "Cass County",
    "Fargo"
  ],
  "dct_issued_s": "20100202",
  "dct_provenance_s": "Princeton",
  "georss_box_s": "46.604252 -97.737526 47.261836 -96.742200",
  "georss_polygon_s": "47.261836 -97.737526 47.261836 -96.742200 46.604252 -96.742200 46.604252 -97.737526 47.261836 -97.737526",
  "layer_slug_s": "princeton-hq37vq27q",
  "layer_id_s": "pulmap-restricted:hq37vq27q",
  "layer_modified_dt": "2014-12-19T16:18:34Z",
  "layer_geom_type_s": "Line",
  "solr_geom": "ENVELOPE(-97.737526, -96.742200, 47.261836, 46.604252)"
}