{
  "uuid": "http://arks.princeton.edu/ark:/88435/h989r5685",
  "dc_description_s": "An accurate map of North and South Carolina with their Indian frontiers, shewing in a distinct manner all the mountains, rivers, swamps, marshes, bays, creeks, harbours, sandbanks and soundings on the coasts; with the roads and Indian paths; as well as the boundary of provincial lines, the several townships and other divisions of the land in both the provinces",
  "dc_format_s": "Scanned Map",
  "dc_identifier_s": "h989r5685",
  "dc_rights_s": "Public",
  "dct_provenance_s": "Princeton",
  "dct_references_s": "{\"http://www.loc.gov/standards/marcxml\":\"https://geowebservices.princeton.edu/download/items/h989r5685/marc.xml\",\"http://iiif.io/api/image\":\"https://libimages1.princeton.edu/loris/pulmap%2Fh9%2F89%2Fr5%2F68%2F5%2F00000001.jp2/info.json\"}",
  "layer_id_s": "h989r5685",
  "layer_slug_s": "princeton-h989r5685",
  "layer_geom_type_s": "Image",
  "layer_modified_dt": "2015-11-23T14:10:15Z",
  "dc_title_s": "An accurate map of North and South Carolina with their Indian frontiers, shewing in a distinct manner all the mountains, rivers, swamps, marshes, bays, creeks, harbours, sandbanks and soundings on the coasts; with the roads and Indian paths; as well as the boundary of provincial lines, the several townships and other divisions of the land in both the provinces",
  "dc_type_s": "Image",
  "dct_spatial_sm": [
    "North Carolina",
    "South Carolina",
    "North Carolina",
    "South Carolina",
    "Sea Islands"
  ],
  "dct_temporal_sm": [
    "1775"
  ],
  "georss_box_s": "33.752878 -84.3218689 36.5880363 -75.4001189",
  "georss_polygon_s": "36.5880363 -84.3218689 36.5880363 -75.4001189 33.752878 -75.4001189 33.752878 -84.3218689 36.5880363 -84.3218689",
  "solr_geom": "ENVELOPE(-84.3218689, -75.4001189, 36.5880363, 33.752878)",
  "solr_year_i": "1775"
}
