{
  "dc_description_s": "This is a map of Cyprus. The map was created by the United States Central Intelligence Agency.",
  "layer_modified_dt": "2015-01-11T17:42:53Z",
  "solr_geom": "ENVELOPE(32.5, 34.5, 35.5, 34.5)",
  "dct_references_s": "{\"http://www.opengis.net/cat/csw/csdgm\": \"https://geowebservices.princeton.edu/download/items/sj1393484/fgdc.xml\", \"http://iiif.io/api/image\": \"https://libimages.princeton.edu/loris/pulmap/sj/13/93/48/4/00000001.jp2/info.json\", \"http://schema.org/thumbnailUrl\": \"https://geowebservices.princeton.edu/download/items/sj1393484/preview.jpg\"}",
  "dc_rights_s": "Public",
  "dct_provenance_s": "Princeton",
  "dc_subject_sm": [
    "Roads",
    "Railroads",
    "Airfield",
    "Political and Administrational Boundaries"
  ],
  "dc_format_s": "Scanned Map",
  "layer_slug_s": "princeton-sj1393484",
  "dc_creator_sm": [
    "Central Intelligence Agency"
  ],
  "dc_type_s": "Image",
  "dc_identifier_s": "sj1393484",
  "dc_publisher_s": "Central Intelligence Agency",
  "dct_spatial_sm": [
    "Cyprus",
    "Europe",
    "Mediterranean"
  ],
  "layer_id_s": "sj1393484",
  "dc_title_s": "Cyprus, 1980",
  "dct_issued_s": "January 1980",
  "layer_geom_type_s": "Image",
  "dc_language_s": "English",
  "geoblacklight_version": "1.0"
}
