{
  "uuid": "http://arks.princeton.edu/ark:/88435/rr172005s",
  "dc_creator_sm": [
    "Sayer, Robert,"
  ],
  "dc_description_s": "A map of the whole continent of America, divided into North and South and West Indies with a copious table fully shewing the several possessions of each European prince & state, as settled by the definitive treaty concluded at Paris Feby. 10th 1763, the clauses of which relative thereto are inserted",
  "dc_format_s": "Scanned Map",
  "dc_identifier_s": "rr172005s",
  "dc_rights_s": "Public",
  "dct_provenance_s": "Princeton",
  "dct_references_s": "{\"http://www.loc.gov/standards/marcxml\":\"https://geowebservices.princeton.edu/download/items/rr172005s/marc.xml\",\"http://iiif.io/api/image\":\"https://geowebservices.princeton.edu/iiif/pulmap%2Frr%2F17%2F20%2F05%2Fs%2F00000001.jp2%2Finfo.json\"}",
  "layer_id_s": "rr172005s",
  "layer_slug_s": "princeton-rr172005s",
  "layer_geom_type_s": "Image",
  "layer_modified_dt": "2015-01-25T02:06:08Z",
  "dc_title_s": "A map of the whole continent of America, divided into North and South and West Indies with a copious table fully shewing the several possessions of each European prince & state, as settled by the definitive treaty concluded at Paris Feby. 10th 1763, the clauses of which relative thereto are inserted",
  "dc_type_s": "Image",
  "dct_spatial_sm": [
    "America"
  ],
  "dct_temporal_sm": [
    "1772"
  ],
  "georss_box_s": "18.9110642 172.4458955 71.389888 -66.9453947",
  "georss_polygon_s": "71.389888 172.4458955 71.389888 -66.9453947 18.9110642 -66.9453947 18.9110642 172.4458955 71.389888 172.4458955",
  "solr_geom": "ENVELOPE(172.4458955, -66.9453947, 71.389888, 18.9110642)",
  "solr_year_i": "1772"
}