{
  "uuid": "http://arks.princeton.edu/ark:/88435/jq085m48x",
  "dc_creator_sm": [
    "Geographic Data Technology, Inc. (GDT)"
  ],
  "dc_description_s": "West Virginia Rivers represents streams and rivers within West Virginia.",
  "dc_format_s": "Shapefile",
  "dc_identifier_s": "jq085m48x",
  "dc_language_s": "English",
  "dc_publisher_s": "Environmental Systems Research Institute, Inc. (ESRI)",
  "dc_rights_s": "Restricted",
  "dc_subject_sm": [
    "line",
    "streams",
    "rivers",
    "perennial",
    "cfcc",
    "Inland Waters"
  ],
  "dc_title_s": "West Virginia Rivers 2002",
  "dc_type_s": "Dataset",
  "dct_references_s": "{\"http://schema.org/downloadUrl\":\"https://geowebservices.princeton.edu/download/items/jq085m48x/data.zip\",\"http://www.opengis.net/def/serviceType/ogc/wfs\":\"https://geowebservices.princeton.edu/pulmap-restricted/geoserver/wfs\",\"http://www.opengis.net/cat/csw/csdgm\":\"https://geowebservices.princeton.edu/download/items/jq085m48x/fgdc.xml\",\"http://www.opengis.net/def/serviceType/ogc/wms\":\"https://geowebservices.princeton.edu/pulmap-restricted/geoserver/wms\",\"http://schema.org/thumbnailUrl\":\"https://geowebservices.princeton.edu/download/items/jq085m48x/preview.jpg\"}",
  "dct_spatial_sm": [
    "United States",
    "West Virginia"
  ],
  "dct_temporal_sm": [
    "1997"
  ],
  "dct_issued_s": "20020401",
  "dct_provenance_s": "Princeton",
  "georss_box_s": "37.203307 -82.616583 40.634876 -77.745825",
  "layer_slug_s": "princeton-jq085m48x",
  "layer_id_s": "pulmap-restricted:jq085m48x",
  "layer_modified_dt": "2014-12-19T16:18:33Z",
  "layer_geom_type_s": "Line",
  "solr_geom": "ENVELOPE(-82.616583, -77.745825, 40.634876, 37.203307)",
  "solr_year_i": "1997"
}